SQLHelper/__init__.py
SQLHelper/backfill.py
SQLHelper/base.py
SQLHelper/helper.py
SQLHelper/logging.py
SQLHelper/main.py
SQLHelper/utils.py
sparksql_helper-0.0.37.dist-info/METADATA
sparksql_helper-0.0.37.dist-info/WHEEL
sparksql_helper-0.0.37.dist-info/top_level.txt
sparksql_helper-0.0.37.dist-info/RECORD
