Metadata-Version: 2.1
Name: sparksql-helper
Version: 0.0.37
Summary: SparkSQL Helper
Home-page: https://github.com/felixzhu17/SparkSqlHelper
Author: Felix Zhu
Author-email: zhu.felix@outlook.com
License: MIT
Platform: UNKNOWN
Requires-Dist: pandas
Requires-Dist: loguru
Requires-Dist: tqdm
Requires-Dist: pyspark
